{"WZNnBxX2vQjsRuJxnFw85Q==":"mbr-1920x1280.jpeg","fSqkzm3eYVEYp4LElfq+YQ==":"mbr-700x467.jpg","U6Ng5tKVw9HpT0Sjz7mTQQ==":"mbr-1-700x467.jpg","ngiz/FGNJIInDDdvJMfGgw==":"mbr-700x463.jpg","fFw6F2wy+caSf3ClMopc5A==":"mbr-700x440.jpg","cmi0AoReTXzjXfGs7qC9rQ==":"mbr-1-1920x1280.jpeg","q0Gpwz0zGw1D/pg6MT/asQ==":"background8.jpg","G/YnXf8fZRZwUPpph2g6qA==":"mbr-96x68.jpg","4NezfuCdqPLsF4KFV4ENCA==":"img_1617%20(2)-1368x1824.jpeg","Hk885w/0N/AC9cqnB4GEiQ==":"download%20(1)-172x172.png","yGCa4G06Qq/bIVwkSWR2RQ==":"img-1711-1368x1824.jpeg","D9fDzVI7CVgpnen9wEIVMQ==":"img_1717%20(1)-676x901.jpg","MQ3Vy3VMTACV6pOn8bOm3g==":"img_1717%20(1)-676x901.jpeg","FekUxe9dSUmTIX5Cq/GTrg==":"img_1495%20(1)-1368x1824.jpg","UXnHTl7qTAHy7c2Ow+zOjQ==":"img_2533%20(3)-676x901.jpg","tZBRu0VI5bBb0PfS79bo+w==":"img-2525-676x507.jpg","uTgNyBhpnUZq16K7ibCTXQ==":"img_2533%20(3)-676x901.jpeg","RlLT9J321+IXcMEGu666LQ==":"img-2526-1368x1026.jpeg","w11sgKweKa8/dJgNl0186w==":"img-2526-2000x1500.jpg","FbVTIz4zs999sw5Ro7a+yQ==":"img_1495%20(2)-676x901.jpg","DqhjG62wFogHf4ECR1G9+w==":"img-1845-1368x1026.jpg","LkNeWa7L051+jwjmXRw2Hw==":"img-1845-2000x1500.jpg","CaP8H3hPkt+IklTyiQ8ZCg==":"img-1717-1368x1824.jpg","GyGyWPObWIWlS8UxgxFmiw==":"img_1711%20(1)-676x901.jpg","rLqkLBvIEbmWLvyP6rmyuQ==":"img_1717%20(1)-2000x2667.jpg","uEshJn1iBZ5ZFykO/QomFw==":"img_1717%20(1)-2000x2667.jpeg","rUiUQJTD6uK4nmF+beJdJQ==":"img_1717%20(1)-2000x2667.jpeg","vuva6c6cPuhd3HRZMo8zpg==":"img-2526-2000x1500.jpeg","kBM/9t0KHPL/jc0N+Bv4Iw==":"img-2527-2000x1500.jpeg","vQFXqaWoCKE+JYuDkvFViQ==":"img_1617%20(1)-676x901.jpg","KsKCfOfpyKgq0+tBx8I5Kg==":"img-1843-676x507.jpg","cRR6DcVc2g+EW/iAnYo14w==":"img-1841-676x901.jpg","GMG0hCDRvr4+D9PsvIVQjQ==":"img-1845-700x525.jpg","4qGlsh6azQLZQozjGGXFvA==":"img-2526-700x525.jpg","ohodzICALRScMJufcHHF9w==":"yellow%20watersports%20rental%20logo%20(2)-122x122.jpg","h/UN6O6KIvkFxLsxnQ8RNA==":"yellow%20watersports%20rental%20logo%20(2)-122x122.jpeg","XgW7B9R6M5GEMxVlBidWYQ==":"yellow%20watersports%20rental%20logo%20(1)-122x122.jpeg","X18GOL+jBkOnbCqhwA+F9g==":"yellow%20watersports%20rental%20logo%20(1)-122x122.jpg","fS6X52rFjN8lCjaDMU3cAQ==":"yellow%20watersports%20rental%20logo%20(1)-122x122.jpeg","NW96hijicQDpZpSdsG43Ag==":"img-2003-2000x2667.jpg","R0U9dyl989aKE5gADsrt4Q==":"img-2003-1254x1672.jpg","fSjrsXbFHNp8qdjurMEuTA==":"img-1986-676x901.jpg","65UoxFYKZph4iJSWpw9ShA==":"img-1994-980x735.jpeg","eQDP6SL1lBCSCyeWsOdMtg==":"img-1987-676x901.jpg","99vVo66WPgDICRkX4J0nOg==":"img-1981-676x901.jpg","wwIQhObJds1Xb6kvNy1dkA==":"img-1843-676x507.jpeg","pa5Dkwo/T1qgW/t0h+fQvA==":"background5.jpg","bQ5Z0xoempVITHlvm70TGQ==":"img-2010-676x471.jpg","PfrKxAptPz7AnM/fJW1Vlg==":"img-2527-1368x1026.jpeg","aUGtfYICbWPKT/OIymzBgA==":"img-2009-676x901.jpg","eukxEPfFBi8Z+erI0i4J1Q==":"img-1986-700x933.jpg","1IfJosT2WG2sJZKD0taYYw==":"img-2061-640x480.jpg","SJebsheXuOrkr+CS6qmrvQ==":"img-2062-640x480.jpeg"}